{"cameraMode":{"drawMode":0,"name":"Shaded","section":"Shading Mode"},"sceneLighting":true,"audioPlay":false,"sceneViewState":{"m_AlwaysRefresh":false,"showFog":true,"showSkybox":true,"showFlares":true,"showImageEffects":true,"showParticleSystems":true,"showVisualEffectGraphs":true,"m_FxEnabled":true},"in2DMode":false,"pivot":{"x":7.045229911804199,"y":-65.16230773925781,"z":-76.78536987304688},"rotation":{"x":-0.4140986502170563,"y":0.18542711436748506,"z":-0.08657372742891312,"w":-0.8869318962097168},"size":113.00420379638672,"orthographic":false}